markdowntable/__init__.py
markdowntable-6.0.0.dist-info/LICENSE
markdowntable-6.0.0.dist-info/METADATA
markdowntable-6.0.0.dist-info/WHEEL
markdowntable-6.0.0.dist-info/top_level.txt
markdowntable-6.0.0.dist-info/RECORD
