Metadata-Version: 2.1
Name: markdowntable
Version: 6.0.0
Summary: Easy way to make markdown code for tables
Home-page: https://github.com/PokestarFan/Python-Markdown-Table
Author: PythonCoderAS
License: MIT
Platform: UNKNOWN
License-File: LICENSE
